fetchcommandwrapper/__init__.py
fetchcommandwrapper/__main__.py
fetchcommandwrapper/version.py
fetchcommandwrapper-1.0.0.data/data/share/fetchcommandwrapper/make.conf
fetchcommandwrapper-1.0.0.dist-info/METADATA
fetchcommandwrapper-1.0.0.dist-info/WHEEL
fetchcommandwrapper-1.0.0.dist-info/entry_points.txt
fetchcommandwrapper-1.0.0.dist-info/top_level.txt
fetchcommandwrapper-1.0.0.dist-info/RECORD
